TheProtocols/__init__.py
TheProtocols/__main__.py
TheProtocols/session.py
TheProtocols/theprotocols.py
TheProtocols/helpers/exceptions.py
TheProtocols/helpers/version.py
TheProtocols/objects/app.py
TheProtocols/objects/calendar.py
TheProtocols/objects/chat.py
TheProtocols/objects/deleted.py
TheProtocols/objects/home.py
TheProtocols/objects/mail.py
TheProtocols/objects/network.py
TheProtocols/objects/notes.py
TheProtocols/objects/photos.py
TheProtocols/objects/reminders.py
TheProtocols/objects/resource.py
TheProtocols/objects/storage.py
TheProtocols/objects/token.py
TheProtocols/objects/user.py
TheProtocols-3.1.0.1.dist-info/LICENSE
TheProtocols-3.1.0.1.dist-info/METADATA
TheProtocols-3.1.0.1.dist-info/WHEEL
TheProtocols-3.1.0.1.dist-info/top_level.txt
TheProtocols-3.1.0.1.dist-info/RECORD
